{
    "source_code": "UK_MWL",
    "source_name": " UK Most Wanted List",
    "source_url": "https://www.nationalcrimeagency.gov.uk/most-wanted-search",
    "persons": [
        {
            "name": "Nana Oppong",
            "about": {
                "Locatio": "Male",
                "Date of Inciden": "41-42",
                "Crim": "Athletic"
            },
            "Extra Info": "Two circular scars above his right eye. A series of small scars on his left hand and fingers. Stomach scar near naval."
        },
        {
            "name": "Mark Francis Roberts",
            "about": {
                "Locatio": "Male",
                "Date of Inciden": "28-29",
                "Crim": "6ft 1in"
            },
            "Extra Info": "From Liverpool. White, 6ft 1in tall, of medium build. Has a 7.6cm scar down his right leg. Heavy eyebrows, right handed; green eyes; potential scar on arm obtained during the attempted robbery."
        },
        {
            "name": "Dean Garforth",
            "about": {
                "Locatio": "Male",
                "Date of Inciden": "29-30",
                "Crim": "5ft 6in"
            },
            "Extra Info": "Born in Liverpool."
        },
        {
            "name": "Callum Michael Allan",
            "about": {
                "Locatio": "Male",
                "Date of Inciden": "23-24",
                "Crim": "182cm"
            },
            "Extra Info": "Allan is around 182cms tall with fine hair, blue eyes, slim build and a Tyneside accent."
        },
        {
            "name": "John James Jones",
            "about": {
                "Locatio": "Male",
                "Date of Inciden": "31-32",
                "Crim": "6ft"
            }
        },
        {
            "name": "Calvin Parris",
            "about": {
                "Locatio": "Male",
                "Date of Inciden": "31-32",
                "Crim": "5ft 11in"
            },
            "Extra Info": "Parris has gold upper teeth."
        },
        {
            "name": "Asim Naveed",
            "about": {
                "Locatio": "Male",
                "Date of Inciden": "29-30",
                "Crim": "6ft 2in"
            },
            "Extra Info": "Naveed has a surgical scar along left wrist."
        },
        {
            "name": "Jack Mayle",
            "about": {
                "Locatio": "Male",
                "Date of Inciden": "30-31",
                "Crim": "5ft 11in"
            },
            "Extra Info": "Born in Croydon, around 5ft 11 in tall and muscular. Diamond tattoo under his left eye, and a tattoo on the outside of his left forearm that reads \u2018Croydon\u2019. Left hand tattooed with \u2018Money never sleeps\u2019, \u201912-20\u2019 and a small heart.  His right hand has an eye design tattoo with hands around it and word \u2018Littles\u2019. On both hands he has tattoos on his fingers reading \u2018trap star\u2019. His neck is tattooed with warriors and religious figures on horses. He has a full back tattoo. May have tried to alter his appearance. He is known to carry weapons; is a regular gym goer and vegan."
        },
        {
            "name": "Richard Wakeling",
            "about": {
                "Locatio": "Male",
                "Date of Inciden": "5'11",
                "Crim": "Slim"
            },
            "Extra Info": "Wakeling has a right lower leg amputation and uses a prosthetic leg. He has family and friends in Ireland, Spain, Canada and Thailand. He requires regular medical treatment."
        },
        {
            "name": "Daniel Dugic",
            "about": {
                "Locatio": "Male",
                "Date of Inciden": "Eastern European",
                "Crim": "Drug trafficking"
            },
            "Extra Info": "Dugic is originally from Serbia"
        },
        {
            "name": "Derek McGraw Ferguson",
            "about": {
                "Locatio": "Male",
                "Date of Inciden": "155 - 160 cm",
                "Crim": "Brown / grey"
            },
            "Extra Info": "Ferguson was born in Glasgow in 1964. He has green/blue eyes and short balding brown/grey hair."
        },
        {
            "name": "Allan Foster",
            "about": {
                "Locatio": "Male",
                "Date of Inciden": "170 - 175 cm",
                "Crim": "Slim"
            },
            "Extra Info": "Foster has links to the Canary Islands and Majorca. He is also known to use the alias Shaun Michael Wilkinson."
        },
        {
            "name": "Kevin Thomas Parle",
            "about": {
                "Locatio": "Male",
                "Date of Inciden": "195 - 200cm",
                "Crim": "Stocky"
            },
            "Extra Info": "Also known as 'Hemp'."
        },
        {
            "name": "Fatah Benlaredj",
            "about": {
                "Date of Inciden": "2007-05-01",
                "Crim": "Rape, Child sexual abuse"
            },
            "Extra Info": "Benlaredj also uses the nickname Samir"
        },
        {
            "name": "Shashi Dhar Sahnan",
            "about": {
                "Date of Inciden": "Male",
                "Crim": "170 - 175 cm"
            },
            "Extra Info": "Born in India, Sahnan has brown eyes and wears an overt hearing aid in his right ear which sits over the ear."
        },
        {
            "name": "John Barton",
            "about": {
                "Locatio": "Male",
                "Date of Inciden": "170 - 175 cm",
                "Crim": "Medium"
            }
        },
        {
            "name": "Rezgar Zengana",
            "about": {
                "Date of Inciden": "Male",
                "Crim": "180 - 185cm"
            },
            "Extra Info": "Zengana is an Iraqi national"
        },
        {
            "name": "Osman Aydeniz",
            "about": {
                "Crim": "Male"
            },
            "Extra Info": "Aydeniz is a Cypriot national"
        },
        {
            "name": "Ozgur Demir",
            "about": {
                "Crim": "Male"
            },
            "Extra Info": "Demir is a Turkish national"
        },
        {
            "name": "Ersin Mustafa",
            "about": {
                "Locatio": "Male",
                "Date of Inciden": "165 - 170 cm"
            }
        },
        {
            "name": "Christakis Philippou",
            "about": {
                "Locatio": "Male",
                "Date of Inciden": "165 - 170 cm",
                "Crim": "Dark / Greying"
            },
            "Extra Info": "Known to use the alias Christakis Chrysostomou"
        },
        {
            "name": "Timur Mehmet",
            "about": {
                "Date of Inciden": "Male",
                "Crim": "175 - 180 cm"
            }
        },
        {
            "name": "Costas Sampson",
            "about": {
                "Locatio": "Male",
                "Date of Inciden": "175 - 180 cm",
                "Crim": "Large"
            },
            "Extra Info": "Sampson is a Cypriot national who is known to use the alias Kostas"
        },
        {
            "name": "Mehmet Salih",
            "about": {
                "Locatio": "Male",
                "Date of Inciden": "165 - 170 cm",
                "Crim": "Brown"
            },
            "Extra Info": "Salih is a Cypriot national. He has a scar on his right eye."
        },
        {
            "name": "Shazad Ghafoor",
            "about": {
                "Locatio": "Male",
                "Crim": "5ft 11 ins"
            },
            "Extra Info": "Has pock mark on right cheek, scar on right of the nose, scar on top of right hand"
        },
        {
            "name": "Jonathon Kelly",
            "about": {
                "Locatio": "Male",
                "Crim": "180cm"
            }
        }
    ]
}